spacy_combo/__init__.py
spacy_combo/combo.py
spacy_combo/encoders.py
spacy_combo/main.py
spacy_combo/models.py
spacy_combo/mst.py
spacy_combo/parser.py
spacy_combo/utils.py
spacy_combo-0.8.1.dist-info/LICENSE.txt
spacy_combo-0.8.1.dist-info/METADATA
spacy_combo-0.8.1.dist-info/WHEEL
spacy_combo-0.8.1.dist-info/top_level.txt
spacy_combo-0.8.1.dist-info/RECORD
