Metadata-Version: 2.1
Name: spacy-combo
Version: 0.8.1
Summary: COMBO wrapper for spaCy
Home-page: https://github.com/KoichiYasuoka/spaCy-COMBO
Author: Koichi Yasuoka
Author-email: yasuoka@kanji.zinbun.kyoto-u.ac.jp
License: MIT
Project-URL: COMBO, https://github.com/360er0/COMBO
Project-URL: Source, https://github.com/KoichiYasuoka/spaCy-COMBO
Project-URL: Tracker, https://github.com/KoichiYasuoka/spaCy-COMBO/issues
Keywords: NLP COMBO spaCy
Classifier: License :: OSI Approved :: MIT License
Classifier: Programming Language :: Python :: 3
Classifier: Operating System :: OS Independent
Classifier: Topic :: Text Processing :: Linguistic
Requires-Python: >=3.6
License-File: LICENSE.txt
Requires-Dist: Keras (>=2.2.4)
Requires-Dist: deplacy (>=2.1.0)
Requires-Dist: joblib (>=0.13.2)
Requires-Dist: numpy (>=1.16.2)
Requires-Dist: scikit-learn (>=0.20.3)
Requires-Dist: spacy (>=2.3.0)
Requires-Dist: sparse (>=0.10.0)
Requires-Dist: tensorflow (>=1.14.0)
